mime_py-0.3.0.dist-info/METADATA
mime_py-0.3.0.dist-info/WHEEL
mime_py-0.3.0.dist-info/license_files/LICENSE
mime/__init__.py
mime/mime.cpython-310-x86_64-linux-gnu.so
mime_py-0.3.0.dist-info/RECORD
