Metadata-Version: 2.1
Name: mime-py
Version: 0.3.0
Classifier: Programming Language :: Rust
Classifier: Programming Language :: Python :: Implementation :: CPython
Classifier: Programming Language :: Python :: Implementation :: PyPy
License-File: LICENSE
Summary: A text processing framework, inspired by Emacs lisp and keyboard macros.
Keywords: scripting,text-processing
License: GPL-3.0
Requires-Python: >=3.7
Project-URL: Source Code, https://github.com/shsms/mime
